pyelternportal/__init__.py
pyelternportal/appointment.py
pyelternportal/attachment.py
pyelternportal/blackboard.py
pyelternportal/const.py
pyelternportal/demo.py
pyelternportal/exception.py
pyelternportal/lesson.py
pyelternportal/letter.py
pyelternportal/message.py
pyelternportal/poll.py
pyelternportal/register.py
pyelternportal/school.py
pyelternportal/schools.py
pyelternportal/sicknote.py
pyelternportal/student.py
pyelternportal-0.0.18.dist-info/METADATA
pyelternportal-0.0.18.dist-info/WHEEL
pyelternportal-0.0.18.dist-info/licenses/LICENSE
pyelternportal-0.0.18.dist-info/RECORD
