Metadata-Version: 2.4
Name: pyelternportal
Version: 0.0.18
Summary: API to retrieve data from Eltern-Portal
Project-URL: Homepage, https://github.com/michull/pyelternportal
Project-URL: Issues, https://github.com/michull/pyelternportal/issues
Author-email: michull <michull@github.com>
License-File: LICENSE
Keywords: elternportal
Classifier: Development Status :: 3 - Alpha
Classifier: Environment :: Console
Classifier: Intended Audience :: Developers
Classifier: License :: OSI Approved :: The Unlicense (Unlicense)
Classifier: Operating System :: OS Independent
Classifier: Programming Language :: Python :: 3.13
Requires-Python: >=3.13
Requires-Dist: aiohttp>=3.10
Requires-Dist: aiozoneinfo>=0.2.1
Requires-Dist: beautifulsoup4>=4.12.3
Requires-Dist: html5lib>=1.1
